udata_ckan/__init__.py
udata_ckan/harvesters.py
udata_ckan/models.py
udata_ckan/schemas/__init__.py
udata_ckan/schemas/ckan.py
udata_ckan/schemas/dkan.py
udata_ckan/translations/udata-ckan.pot
udata_ckan/translations/fr/LC_MESSAGES/udata-ckan.mo
udata_ckan/translations/fr/LC_MESSAGES/udata-ckan.po
udata_ckan/translations/pt/LC_MESSAGES/udata-ckan.mo
udata_ckan/translations/pt/LC_MESSAGES/udata-ckan.po
udata_ckan-4.0.2.dist-info/METADATA
udata_ckan-4.0.2.dist-info/WHEEL
udata_ckan-4.0.2.dist-info/entry_points.txt
udata_ckan-4.0.2.dist-info/top_level.txt
udata_ckan-4.0.2.dist-info/RECORD
