Metadata-Version: 2.1
Name: udata-ckan
Version: 4.0.2
Summary: CKAN integration for udata
Home-page: https://github.com/opendatateam/udata-ckan
Author: OpenDataTeam
Author-email: udata@opendata.team
License: AGPL
Keywords: udata harvester CKAN
Classifier: Development Status :: 3 - Alpha
Classifier: Programming Language :: Python
Classifier: Environment :: Web Environment
Classifier: Operating System :: OS Independent
Classifier: Intended Audience :: Developers
Classifier: Topic :: System :: Software Distribution
Classifier: Programming Language :: Python
Classifier: Programming Language :: Python :: 3
Classifier: Programming Language :: Python :: 3.7
Classifier: Topic :: Software Development :: Libraries :: Python Modules
Requires-Python: >=3.7
Requires-Dist: udata >=10.3.0
Requires-Dist: humanfriendly ==10.0
Provides-Extra: test
Requires-Dist: mock ==5.2.0 ; extra == 'test'
Requires-Dist: pytest ==8.3.5 ; extra == 'test'
Requires-Dist: pytest-flask ==1.3.0 ; extra == 'test'
Requires-Dist: pytest-sugar ==1.0.0 ; extra == 'test'
Requires-Dist: requests-mock ==1.12.1 ; extra == 'test'
